yolotolabelme.py
yolo_to_labelme-0.0.8.dist-info/LICENSE
yolo_to_labelme-0.0.8.dist-info/METADATA
yolo_to_labelme-0.0.8.dist-info/WHEEL
yolo_to_labelme-0.0.8.dist-info/entry_points.txt
yolo_to_labelme-0.0.8.dist-info/top_level.txt
yolo_to_labelme-0.0.8.dist-info/RECORD
