Metadata-Version: 2.1
Name: yolo-to-labelme
Version: 0.0.8
Summary: A python script for converting annotation format(yolo-txt to labelme-json)
Author-email: Adeel Waheed <itsadeelemail@gmail.com>
Project-URL: Homepage, https://github.com/adeel-maker/yolotolabelme
Project-URL: Bug Tracker, https://github.com/adeel-maker/yolotolabelme/issues
Classifier: Programming Language :: Python :: 3
Classifier: License :: OSI Approved :: MIT License
Classifier: Operating System :: OS Independent
Requires-Python: >=3.6
License-File: LICENSE
